INPR.py
INPR/__init__.py
INPR/get_details.py
INPR/get_num_plate.py
INPR/inpr.py
INPR/utils.py
INPR-1.0.1.dist-info/LICENSE
INPR-1.0.1.dist-info/METADATA
INPR-1.0.1.dist-info/WHEEL
INPR-1.0.1.dist-info/top_level.txt
INPR-1.0.1.dist-info/RECORD
