Metadata-Version: 2.1
Name: INPR
Version: 1.0.1
Summary: A deep learning based library to detect indian number plates
Home-page: https://github.com/patrickn699/INPR
Author: Prathmesh Patil
Author-email: prathmesh.patil8899@gmail.com
License: UNKNOWN
Download-URL: https://github.com/patrickn699/INPR.git
Keywords: Deep Learning,Computer Vision,Pytorch,Detectron2
Platform: UNKNOWN
Classifier: Programming Language :: Python :: 3
Classifier: License :: OSI Approved :: MIT License
Classifier: Operating System :: OS Independent
Requires-Python: >=3.6
License-File: LICENSE
Requires-Dist: beautifulsoup4 (==4.9.3)
Requires-Dist: Cython (==0.29.23)
Requires-Dist: easyocr (==1.3.1)
Requires-Dist: numpy (==1.20.2)
Requires-Dist: opencv-python (==4.5.1.48)
Requires-Dist: pandas (==1.1.5)
Requires-Dist: pycocotools (==2.0.2)
Requires-Dist: selenium (==3.141.0)
Requires-Dist: matplotlib
Requires-Dist: pyyaml (==5.1)
